pyge/__init__.py
pyge/__main__.py
pyge/citydb.py
pyge/person.py
pyge/persondb.py
pyge/uscities.csv
pyge-1.0.2.dist-info/LICENSE
pyge-1.0.2.dist-info/METADATA
pyge-1.0.2.dist-info/WHEEL
pyge-1.0.2.dist-info/entry_points.txt
pyge-1.0.2.dist-info/top_level.txt
pyge-1.0.2.dist-info/RECORD
